lib/model/__init__.py
lib/model/dto.py
lib/model/models.py
lib/service/__init__.py
lib/service/base.py
lib_pessoa_end-0.1.0.dist-info/METADATA
lib_pessoa_end-0.1.0.dist-info/WHEEL
lib_pessoa_end-0.1.0.dist-info/top_level.txt
lib_pessoa_end-0.1.0.dist-info/RECORD
