Metadata-Version: 2.4
Name: lib_pessoa_end
Version: 0.1.0
Summary: Uma lib MVC simples da Hero com banco de dados em memória.
Author-email: comunisca <lumatavares501@gmail.com>
License: MIT
Project-URL: Homepage, https://github.com/LumaTavares/Lib_ps2
Requires-Python: >=3.8
Requires-Dist: fastapi>=0.110.0
Requires-Dist: uvicorn>=0.27.0
